docker/__init__.py
docker/errors.py
docker/helpers.py
docker/manager.py
docker_wrapper-2.1.2.dist-info/DESCRIPTION.rst
docker_wrapper-2.1.2.dist-info/METADATA
docker_wrapper-2.1.2.dist-info/metadata.json
docker_wrapper-2.1.2.dist-info/RECORD
docker_wrapper-2.1.2.dist-info/top_level.txt
docker_wrapper-2.1.2.dist-info/WHEEL
tests/__init__.py
tests/test_helpers.py
tests/test_manager.py
