Metadata-Version: 2.0
Name: docker-wrapper
Version: 2.1.2
Summary: Docker Wrapper for Python
Home-page: http://github.com/frigg/docker-wrapper-py
Author: Fredrik Carlsen
Author-email: fredrik@carlsen.io
License: MIT
Platform: UNKNOWN
Classifier: Programming Language :: Python
Classifier: Programming Language :: Python :: 2.7
Classifier: Programming Language :: Python :: 3.3
Classifier: Programming Language :: Python :: 3.4
Classifier: Topic :: Software Development :: Libraries :: Python Modules
Classifier: Operating System :: OS Independent
Classifier: Natural Language :: English
